sqlite_ai-0.7.58.data/purelib/sqliteai/__init__.py
sqlite_ai-0.7.58.data/purelib/sqliteai/_version.py
sqlite_ai-0.7.58.data/purelib/sqliteai/binaries/cpu/ai.dll
sqlite_ai-0.7.58.data/purelib/sqliteai/binaries/gpu/ai.dll
sqlite_ai-0.7.58.dist-info/licenses/LICENSE.md
sqlite_ai-0.7.58.dist-info/METADATA
sqlite_ai-0.7.58.dist-info/WHEEL
sqlite_ai-0.7.58.dist-info/top_level.txt
sqlite_ai-0.7.58.dist-info/RECORD
