Metadata-Version: 2.4
Name: sqlite-ai
Version: 0.7.58
Summary: Python prebuilt binaries for SQLite AI extension for all supported platforms and architectures.
Author: SQLite AI Team
License-Expression: LicenseRef-Elastic-2.0-Modified-For-Open-Source-Use
Project-URL: Homepage, https://sqlite.ai
Project-URL: Documentation, https://github.com/sqliteai/sqlite-ai/blob/main/API.md
Project-URL: Repository, https://github.com/sqliteai/sqlite-ai
Project-URL: Issues, https://github.com/sqliteai/sqlite-ai/issues
Classifier: Programming Language :: Python :: 3
Classifier: Operating System :: Microsoft :: Windows
Requires-Python: >=3
License-File: LICENSE.md
Dynamic: classifier
Dynamic: license-file
